npmrc2yarnrc/__init__.py
npmrc2yarnrc-0.3.0.dist-info/entry_points.txt
npmrc2yarnrc-0.3.0.dist-info/WHEEL
npmrc2yarnrc-0.3.0.dist-info/METADATA
npmrc2yarnrc-0.3.0.dist-info/RECORD
