Metadata-Version: 2.1
Name: npmrc2yarnrc
Version: 0.3.0
Summary: 
Author: Willem Thiart
Author-email: himself@willemthiart.com
Requires-Python: >=3.7,<4.0
Classifier: Programming Language :: Python :: 3
Classifier: Programming Language :: Python :: 3.7
Classifier: Programming Language :: Python :: 3.8
Classifier: Programming Language :: Python :: 3.9
Requires-Dist: PyYAML (>=5.4.1,<6.0.0)
Requires-Dist: mergedeep (>=1.3.4,<2.0.0)
